{
  "api": {
    "name": "EmulationPlugin",
    "slug": "emulationplugin",
    "docs": "",
    "tags": [],
    "methods": [
      {
        "name": "echo",
        "signature": "(options: { value: string; }) => any",
        "parameters": [
          {
            "name": "options",
            "docs": "",
            "type": "{ value: string; }"
          }
        ],
        "returns": "any",
        "tags": [],
        "docs": "",
        "complexTypes": [],
        "slug": "echo"
      },
      {
        "name": "addListener",
        "signature": "(eventName: 'onNewData', listenerFunc: (data: string) => void) => PluginListenerHandle",
        "parameters": [
          {
            "name": "eventName",
            "docs": "",
            "type": "\"onNewData\""
          },
          {
            "name": "listenerFunc",
            "docs": "",
            "type": "(data: string) => void"
          }
        ],
        "returns": "PluginListenerHandle",
        "tags": [],
        "docs": "",
        "complexTypes": [
          "PluginListenerHandle"
        ],
        "slug": "addlistener"
      }
    ],
    "properties": []
  },
  "interfaces": [
    {
      "name": "PluginListenerHandle",
      "slug": "pluginlistenerhandle",
      "docs": "",
      "tags": [],
      "methods": [],
      "properties": [
        {
          "name": "remove",
          "tags": [],
          "docs": "",
          "complexTypes": [],
          "type": "() => void"
        }
      ]
    }
  ],
  "enums": []
}